pypipemachine/__init__.py
pypipemachine/exec_map.py
pypipemachine/magic_filter.py
pypipemachine/router.py
pypipemachine/state.py
pypipemachine/transition.py
pypipemachine-0.0.1.dist-info/METADATA
pypipemachine-0.0.1.dist-info/WHEEL
pypipemachine-0.0.1.dist-info/top_level.txt
pypipemachine-0.0.1.dist-info/RECORD
